MANIFEST.in
README.md
pyproject.toml
setup.py
flydra_core/Roots3And4.c
flydra_core/Roots3And4.h
flydra_core/_Roots3And4.c
flydra_core/_Roots3And4.pxd
flydra_core/_Roots3And4.pyx
flydra_core/__init__.py
flydra_core/_fastgeom.c
flydra_core/_fastgeom.pxd
flydra_core/_fastgeom.pyx
flydra_core/_flydra_tracked_object.c
flydra_core/_flydra_tracked_object.pyx
flydra_core/_mahalanobis.c
flydra_core/_mahalanobis.pxd
flydra_core/_mahalanobis.pyx
flydra_core/_pmat_jacobian.c
flydra_core/_pmat_jacobian.pxd
flydra_core/_pmat_jacobian.pyx
flydra_core/_pmat_jacobian_water.c
flydra_core/_pmat_jacobian_water.pxd
flydra_core/_pmat_jacobian_water.pyx
flydra_core/_reconstruct_utils.c
flydra_core/_reconstruct_utils.pyx
flydra_core/_refraction.c
flydra_core/_refraction.pxd
flydra_core/_refraction.pyx
flydra_core/align.py
flydra_core/common_variables.py
flydra_core/data_descriptions.py
flydra_core/debuglock.py
flydra_core/flydra_server_art.png
flydra_core/flydra_socket.py
flydra_core/geom.py
flydra_core/reconstruct.py
flydra_core/test_refraction.py
flydra_core/undistort.py
flydra_core/version.py
flydra_core/water.py
flydra_core.egg-info/PKG-INFO
flydra_core.egg-info/SOURCES.txt
flydra_core.egg-info/dependency_links.txt
flydra_core.egg-info/entry_points.txt
flydra_core.egg-info/requires.txt
flydra_core.egg-info/top_level.txt
flydra_core/kalman/__init__.py
flydra_core/kalman/dynamic_models.py
flydra_core/kalman/ekf.py
flydra_core/kalman/flydra_kalman_utils.py
flydra_core/kalman/flydra_tracker.py
flydra_core/kalman/lsprofcalltree.py
flydra_core/kalman/ori_smooth.py
flydra_core/kalman/point_prob.py