Metadata-Version: 2.4
Name: flydra_core
Version: 0.7.21
Summary: flydra mainbrain and core lib
Author-email: Andrew Straw <strawman@astraw.com>
Maintainer-email: Andrew Straw <strawman@astraw.com>
Project-URL: homepage, https://github.com/strawlab/flydra
Requires-Python: >=3.8
Requires-Dist: numpy>=1.19
Requires-Dist: tables>=3.9.0
Requires-Dist: cgkit1>=1.3.0
Requires-Dist: pymvg>=2.1.0
Requires-Dist: adskalman
Requires-Dist: scipy
Requires-Dist: six
